charlink/__init__.py
charlink/admin.py
charlink/apps.py
charlink/auth_hooks.py
charlink/decorators.py
charlink/forms.py
charlink/models.py
charlink/urls.py
charlink/utils.py
charlink/views.py
charlink/app_imports/__init__.py
charlink/app_imports/utils.py
charlink/imports/__init__.py
charlink/imports/aa_contacts.py
charlink/imports/afat.py
charlink/imports/corpstats.py
charlink/imports/corptools.py
charlink/imports/marketmanager.py
charlink/imports/memberaudit.py
charlink/imports/miningtaxes.py
charlink/imports/moonmining.py
charlink/imports/moonstuff.py
charlink/imports/structures.py
charlink/imports/allianceauth/__init__.py
charlink/imports/allianceauth/authentication.py
charlink/imports/allianceauth/corputils.py
charlink/locale/en/LC_MESSAGES/django.mo
charlink/locale/en/LC_MESSAGES/django.po
charlink/locale/it_IT/LC_MESSAGES/django.mo
charlink/locale/it_IT/LC_MESSAGES/django.po
charlink/management/__init__.py
charlink/management/commands/__init__.py
charlink/management/commands/charlink_reset_selections.py
charlink/migrations/0001_initial.py
charlink/migrations/0002_appsettings_alter_general_options.py
charlink/migrations/0003_compliancefilter.py
charlink/migrations/0004_alter_appsettings_default_selection.py
charlink/migrations/__init__.py
charlink/static/charlink/css/added-icons.css
charlink/templates/charlink/admin_imported_apps.html
charlink/templates/charlink/app_audit.html
charlink/templates/charlink/audit.html
charlink/templates/charlink/base.html
charlink/templates/charlink/charlink.html
charlink/templates/charlink/dashboard_login.html
charlink/templates/charlink/menu-left.html
charlink/templates/charlink/menu-right.html
charlink/templates/charlink/search.html
charlink/templates/charlink/user_audit.html
charlink/templatetags/__init__.py
charlink/templatetags/charlink_versioned_static.py
charlink/templatetags/charlinkutils.py
charlink/tests/__init__.py
charlink/tests/test_app_imports.py
charlink/tests/test_auth_hooks.py
charlink/tests/test_decorators.py
aa_charlink-1.12.1.dist-info/licenses/LICENSE
aa_charlink-1.12.1.dist-info/WHEEL
aa_charlink-1.12.1.dist-info/METADATA
aa_charlink-1.12.1.dist-info/RECORD
