Metadata-Version: 2.4
Name: aa-charlink
Version: 1.12.1
Summary: Character Linker for Alliance Auth
Keywords: allianceauth,eveonline,allianceauth_charlink,charlink
Author-email: Matteo Ghia <matteo.ghia@yahoo.it>
Requires-Python: ~=3.10
Classifier: Environment :: Web Environment
Classifier: Framework :: Django
Classifier: Framework :: Django :: 4
Classifier: Framework :: Django :: 4.2
Classifier: Operating System :: POSIX :: Linux
Classifier: Development Status :: 5 - Production/Stable
Classifier: Intended Audience :: Developers
Classifier: License :: OSI Approved :: GNU General Public License v3 (GPLv3)
Classifier: Natural Language :: English
Classifier: Programming Language :: Python :: 3
Classifier: Programming Language :: Python :: 3.10
Classifier: Programming Language :: Python :: 3.11
Classifier: Programming Language :: Python :: 3.12
Classifier: Programming Language :: Python :: 3.13
Classifier: Topic :: Internet :: WWW/HTTP
Classifier: Topic :: Internet :: WWW/HTTP :: Dynamic Content
License-File: LICENSE
Requires-Dist: allianceauth~=4.6
Requires-Dist: allianceauth-app-utils>=1.14,<3.0
Project-URL: Changelog, https://github.com/Maestro-Zacht/aa-charlink/releases
Project-URL: Homepage, https://github.com/Maestro-Zacht/aa-charlink
Project-URL: Source, https://github.com/Maestro-Zacht/aa-charlink
Project-URL: Tracker, https://github.com/Maestro-Zacht/aa-charlink/issues
